{"stream_id":"L3-812108","level":3,"seed":812108,"params":{"v0":10000,"round_us":60000000,"lambda_j":0.2,"p_jump":0.2,"lambda_a":4.0,"alpha":0.3,"delta0":8.0},"event_stream":[{"t_us":210582,"type":"arrival","trader":"informed","side_intent":null,"u_accept":null},{"t_us":331397,"type":"arrival","trader":"informed","side_intent":null,"u_accept":null},{"t_us":928234,"type":"arrival","trader":"noise","side_intent":"buy","u_accept":0.862168356474915},{"t_us":991418,"type":"arrival","trader":"noise","side_intent":"sell","u_accept":0.15746969308747194},{"t_us":1021307,"type":"arrival","trader":"informed","side_intent":null,"u_accept":null},{"t_us":1086256,"type":"arrival","trader":"informed","side_intent":null,"u_accept":null},{"t_us":1401993,"type":"arrival","trader":"informed","side_intent":null,"u_accept":null},{"t_us":1647696,"type":"arrival","trader":"noise","side_intent":"sell","u_accept":0.13610219809269175},{"t_us":1843143,"type":"arrival","trader":"noise","side_intent":"sell","u_accept":0.5830305511592494},{"t_us":2054512,"type":"arrival","trader":"noise","side_intent":"buy","u_accept":0.4162536213178263},{"t_us":2383735,"type":"arrival","trader":"noise","side_intent":"buy","u_accept":0.24911546611949276},{"t_us":2428983,"type":"arrival","trader":"noise","side_intent":"sell","u_accept":0.4208939062466437},{"t_us":2857743,"type":"arrival","trader":"informed","side_intent":null,"u_accept":null},{"t_us":2879347,"type":"arrival","trader":"noise","side_intent":"buy","u_accept":0.0977444546761872},{"t_us":3205972,"type":"arrival","trader":"noise","side_intent":"buy","u_accept":0.7782480420783279},{"t_us":3260847,"type":"arrival","trader":"informed","side_intent":null,"u_accept":null},{"t_us":3531831,"type":"arrival","trader":"noise","side_intent":"buy","u_accept":0.747282882718634},{"t_us":3915047,"type":"jump","size":-6},{"t_us":4170587,"type":"arrival","trader":"noise","side_intent":"sell","u_accept":0.49064904977714185},{"t_us":4214369,"type":"arrival","trader":"noise","side_intent":"buy","u_accept":0.12923702772099188},{"t_us":5636885,"type":"arrival","trader":"noise","side_intent":"buy","u_accept":0.8841469485106822},{"t_us":6318301,"type":"arrival","trader":"noise","side_intent":"buy","u_accept":0.20441776358344277},{"t_us":6542329,"type":"arrival","trader":"informed","side_intent":null,"u_accept":null},{"t_us":6647705,"type":"arrival","trader":"informed","side_intent":null,"u_accept":null},{"t_us":6778895,"type":"arrival","trader":"noise","side_intent":"buy","u_accept":0.39659419696116194},{"t_us":6971563,"type":"arrival","trader":"noise","side_intent":"sell","u_accept":0.7993005467006893},{"t_us":7261564,"type":"arrival","trader":"informed","side_intent":null,"u_accept":null},{"t_us":7555146,"type":"arrival","trader":"noise","side_intent":"sell","u_accept":0.2897581435180704},{"t_us":7589266,"type":"arrival","trader":"informed","side_intent":null,"u_accept":null},{"t_us":8304376,"type":"arrival","trader":"informed","side_intent":null,"u_accept":null},{"t_us":8409988,"type":"jump","size":6},{"t_us":8556742,"type":"arrival","trader":"informed","side_intent":null,"u_accept":null},{"t_us":8944787,"type":"arrival","trader":"noise","side_intent":"buy","u_accept":0.8283259461901865},{"t_us":9008459,"type":"arrival","trader":"noise","side_intent":"sell","u_accept":0.25014176779442854},{"t_us":9182056,"type":"arrival","trader":"noise","side_intent":"buy","u_accept":0.9095004895893595},{"t_us":9538329,"type":"arrival","trader":"noise","side_intent":"sell","u_accept":0.2931860854979187},{"t_us":9603790,"type":"arrival","trader":"noise","side_intent":"buy","u_accept":0.8241271767210671},{"t_us":10278972,"type":"arrival","trader":"informed","side_intent":null,"u_accept":null},{"t_us":10327693,"type":"arrival","trader":"informed","side_intent":null,"u_accept":null},{"t_us":10426626,"type":"arrival","trader":"noise","side_intent":"buy","u_accept":0.2184949229501405},{"t_us":10748458,"type":"arrival","trader":"noise","side_intent":"sell","u_accept":0.6464111175497038},{"t_us":10776060,"type":"arrival","trader":"noise","side_intent":"buy","u_accept":0.5449412512706395},{"t_us":10870855,"type":"arrival","trader":"informed","side_intent":null,"u_accept":null},{"t_us":11170488,"type":"arrival","trader":"noise","side_intent":"sell","u_accept":0.39984012898308696},{"t_us":11210013,"type":"arrival","trader":"noise","side_intent":"buy","u_accept":0.17958789081081694},{"t_us":11485597,"type":"arrival","trader":"noise","side_intent":"buy","u_accept":0.8611881815435135},{"t_us":11714800,"type":"arrival","trader":"noise","side_intent":"sell","u_accept":0.05666836292217914},{"t_us":11863096,"type":"arrival","trader":"noise","side_intent":"sell","u_accept":0.44241387899811124},{"t_us":11891056,"type":"arrival","trader":"informed","side_intent":null,"u_accept":null},{"t_us":12359634,"type":"arrival","trader":"noise","side_intent":"buy","u_accept":0.23103456071918615},{"t_us":12651286,"type":"jump","size":-7},{"t_us":12773600,"type":"arrival","trader":"noise","side_intent":"buy","u_accept":0.3896723672789859},{"t_us":12830358,"type":"arrival","trader":"informed","side_intent":null,"u_accept":null},{"t_us":12942449,"type":"arrival","trader":"noise","side_intent":"sell","u_accept":0.2541948369059477},{"t_us":13025768,"type":"arrival","trader":"noise","side_intent":"sell","u_accept":0.364334290418836},{"t_us":13248043,"type":"arrival","trader":"noise","side_intent":"buy","u_accept":0.1499072467870185},{"t_us":13304082,"type":"arrival","trader":"noise","side_intent":"sell","u_accept":0.27693726353173986},{"t_us":13980741,"type":"arrival","trader":"informed","side_intent":null,"u_accept":null},{"t_us":15130006,"type":"jump","size":-10},{"t_us":15221925,"type":"arrival","trader":"noise","side_intent":"sell","u_accept":0.7559670621617419},{"t_us":15410010,"type":"jump","size":10},{"t_us":15446620,"type":"arrival","trader":"noise","side_intent":"buy","u_accept":0.18819946593256476},{"t_us":15544660,"type":"arrival","trader":"noise","side_intent":"sell","u_accept":0.5493299196259204},{"t_us":15693719,"type":"arrival","trader":"noise","side_intent":"buy","u_accept":0.9098678130875093},{"t_us":15742469,"type":"arrival","trader":"informed","side_intent":null,"u_accept":null},{"t_us":16159568,"type":"arrival","trader":"noise","side_intent":"sell","u_accept":0.9232879487314675},{"t_us":17014363,"type":"arrival","trader":"noise","side_intent":"buy","u_accept":0.937624500400832},{"t_us":17370313,"type":"jump","size":-11},{"t_us":17773006,"type":"arrival","trader":"noise","side_intent":"buy","u_accept":0.7987034272761271},{"t_us":17854543,"type":"arrival","trader":"informed","side_intent":null,"u_accept":null},{"t_us":17927603,"type":"arrival","trader":"informed","side_intent":null,"u_accept":null},{"t_us":18045091,"type":"arrival","trader":"noise","side_intent":"sell","u_accept":0.6572104820704712},{"t_us":18075274,"type":"arrival","trader":"noise","side_intent":"buy","u_accept":0.2946720353176149},{"t_us":18080560,"type":"arrival","trader":"noise","side_intent":"buy","u_accept":0.34595493182374815},{"t_us":18087925,"type":"arrival","trader":"noise","side_intent":"sell","u_accept":0.8210541063784973},{"t_us":18343852,"type":"arrival","trader":"noise","side_intent":"buy","u_accept":0.28982245811912877},{"t_us":18425685,"type":"arrival","trader":"noise","side_intent":"buy","u_accept":0.24012212330493832},{"t_us":18707730,"type":"arrival","trader":"noise","side_intent":"buy","u_accept":0.4436161637927788},{"t_us":18711342,"type":"arrival","trader":"informed","side_intent":null,"u_accept":null},{"t_us":18966669,"type":"arrival","trader":"noise","side_intent":"sell","u_accept":0.28970580301724214},{"t_us":19016618,"type":"arrival","trader":"noise","side_intent":"sell","u_accept":0.11677185158874359},{"t_us":19075409,"type":"arrival","trader":"noise","side_intent":"sell","u_accept":0.5757228506463513},{"t_us":19091762,"type":"arrival","trader":"informed","side_intent":null,"u_accept":null},{"t_us":19750098,"type":"arrival","trader":"informed","side_intent":null,"u_accept":null},{"t_us":19854503,"type":"arrival","trader":"noise","side_intent":"buy","u_accept":0.6826174846081557},{"t_us":20094181,"type":"arrival","trader":"noise","side_intent":"buy","u_accept":0.1483599496953768},{"t_us":20119679,"type":"arrival","trader":"noise","side_intent":"buy","u_accept":0.5614444795002265},{"t_us":20342799,"type":"arrival","trader":"informed","side_intent":null,"u_accept":null},{"t_us":20450270,"type":"arrival","trader":"noise","side_intent":"buy","u_accept":0.8669020837530509},{"t_us":20743770,"type":"arrival","trader":"noise","side_intent":"buy","u_accept":0.22886270627583993},{"t_us":20809701,"type":"arrival","trader":"informed","side_intent":null,"u_accept":null},{"t_us":20897545,"type":"arrival","trader":"noise","side_intent":"sell","u_accept":0.6698009693025668},{"t_us":20992194,"type":"arrival","trader":"informed","side_intent":null,"u_accept":null},{"t_us":21047617,"type":"arrival","trader":"informed","side_intent":null,"u_accept":null},{"t_us":21099294,"type":"jump","size":-1},{"t_us":21918734,"type":"arrival","trader":"noise","side_intent":"sell","u_accept":0.11392299478882484},{"t_us":22073162,"type":"arrival","trader":"noise","side_intent":"buy","u_accept":0.8159167924665965},{"t_us":22164241,"type":"arrival","trader":"informed","side_intent":null,"u_accept":null},{"t_us":22442329,"type":"arrival","trader":"noise","side_intent":"buy","u_accept":0.7674250743592012},{"t_us":22538150,"type":"arrival","trader":"noise","side_intent":"sell","u_accept":0.962402111608718},{"t_us":22908819,"type":"arrival","trader":"noise","side_intent":"sell","u_accept":0.25089883499765164},{"t_us":23048437,"type":"arrival","trader":"noise","side_intent":"sell","u_accept":0.7572152563855693},{"t_us":23287653,"type":"arrival","trader":"informed","side_intent":null,"u_accept":null},{"t_us":23310790,"type":"arrival","trader":"noise","side_intent":"buy","u_accept":0.15045329989252287},{"t_us":23349328,"type":"arrival","trader":"noise","side_intent":"buy","u_accept":0.21625167755909713},{"t_us":23610023,"type":"arrival","trader":"noise","side_intent":"sell","u_accept":0.6983661682997773},{"t_us":23661894,"type":"arrival","trader":"noise","side_intent":"buy","u_accept":0.04783437963577275},{"t_us":23790617,"type":"arrival","trader":"noise","side_intent":"sell","u_accept":0.7847915717954544},{"t_us":23986554,"type":"jump","size":3},{"t_us":24031103,"type":"arrival","trader":"informed","side_intent":null,"u_accept":null},{"t_us":24163468,"type":"arrival","trader":"noise","side_intent":"sell","u_accept":0.22013437275375392},{"t_us":24460380,"type":"arrival","trader":"informed","side_intent":null,"u_accept":null},{"t_us":24841185,"type":"arrival","trader":"noise","side_intent":"buy","u_accept":0.13006939453530086},{"t_us":24963303,"type":"arrival","trader":"informed","side_intent":null,"u_accept":null},{"t_us":25513777,"type":"arrival","trader":"informed","side_intent":null,"u_accept":null},{"t_us":25573009,"type":"jump","size":-14},{"t_us":25630474,"type":"arrival","trader":"noise","side_intent":"buy","u_accept":0.7533633110554127},{"t_us":25730784,"type":"arrival","trader":"noise","side_intent":"sell","u_accept":0.5371450897975092},{"t_us":25969121,"type":"arrival","trader":"informed","side_intent":null,"u_accept":null},{"t_us":25977374,"type":"arrival","trader":"informed","side_intent":null,"u_accept":null},{"t_us":26063411,"type":"arrival","trader":"noise","side_intent":"sell","u_accept":0.3762923348308367},{"t_us":26084789,"type":"arrival","trader":"informed","side_intent":null,"u_accept":null},{"t_us":26145246,"type":"arrival","trader":"noise","side_intent":"sell","u_accept":0.02161761005750229},{"t_us":26217465,"type":"arrival","trader":"informed","side_intent":null,"u_accept":null},{"t_us":26297972,"type":"arrival","trader":"noise","side_intent":"buy","u_accept":0.3806387311736479},{"t_us":26330978,"type":"arrival","trader":"noise","side_intent":"buy","u_accept":0.823337297717956},{"t_us":26464717,"type":"arrival","trader":"noise","side_intent":"buy","u_accept":0.9357968555571179},{"t_us":26471203,"type":"arrival","trader":"informed","side_intent":null,"u_accept":null},{"t_us":26897285,"type":"arrival","trader":"informed","side_intent":null,"u_accept":null},{"t_us":27249004,"type":"arrival","trader":"informed","side_intent":null,"u_accept":null},{"t_us":27532104,"type":"arrival","trader":"noise","side_intent":"sell","u_accept":0.18755015729605962},{"t_us":27777269,"type":"arrival","trader":"informed","side_intent":null,"u_accept":null},{"t_us":27996850,"type":"arrival","trader":"noise","side_intent":"buy","u_accept":0.17033709460546353},{"t_us":28483834,"type":"arrival","trader":"noise","side_intent":"buy","u_accept":0.8931640315916917},{"t_us":28524770,"type":"arrival","trader":"informed","side_intent":null,"u_accept":null},{"t_us":28704722,"type":"arrival","trader":"informed","side_intent":null,"u_accept":null},{"t_us":28717553,"type":"arrival","trader":"noise","side_intent":"buy","u_accept":0.7458506814441521},{"t_us":29060951,"type":"arrival","trader":"noise","side_intent":"sell","u_accept":0.8807537277162647},{"t_us":29511346,"type":"jump","size":-4},{"t_us":29563428,"type":"arrival","trader":"noise","side_intent":"buy","u_accept":0.690210407208139},{"t_us":29760939,"type":"arrival","trader":"informed","side_intent":null,"u_accept":null},{"t_us":29849729,"type":"arrival","trader":"noise","side_intent":"sell","u_accept":0.37507800682624026},{"t_us":29995565,"type":"arrival","trader":"noise","side_intent":"sell","u_accept":0.6366122774971237},{"t_us":30515197,"type":"arrival","trader":"informed","side_intent":null,"u_accept":null},{"t_us":30773166,"type":"arrival","trader":"noise","side_intent":"sell","u_accept":0.8285946424436719},{"t_us":30874734,"type":"arrival","trader":"informed","side_intent":null,"u_accept":null},{"t_us":30940591,"type":"arrival","trader":"noise","side_intent":"buy","u_accept":0.404438148464658},{"t_us":30941266,"type":"arrival","trader":"noise","side_intent":"sell","u_accept":0.6811348491938024},{"t_us":31083471,"type":"arrival","trader":"informed","side_intent":null,"u_accept":null},{"t_us":31166103,"type":"arrival","trader":"informed","side_intent":null,"u_accept":null},{"t_us":31314196,"type":"arrival","trader":"noise","side_intent":"buy","u_accept":0.5506679103730737},{"t_us":31559716,"type":"arrival","trader":"noise","side_intent":"buy","u_accept":0.974951397889452},{"t_us":31659841,"type":"arrival","trader":"informed","side_intent":null,"u_accept":null},{"t_us":32109284,"type":"arrival","trader":"informed","side_intent":null,"u_accept":null},{"t_us":32556151,"type":"arrival","trader":"informed","side_intent":null,"u_accept":null},{"t_us":33039261,"type":"arrival","trader":"noise","side_intent":"sell","u_accept":0.009153674969205383},{"t_us":33570298,"type":"arrival","trader":"informed","side_intent":null,"u_accept":null},{"t_us":33699967,"type":"arrival","trader":"informed","side_intent":null,"u_accept":null},{"t_us":33817191,"type":"arrival","trader":"noise","side_intent":"buy","u_accept":0.8767071182276605},{"t_us":34102350,"type":"arrival","trader":"noise","side_intent":"sell","u_accept":0.02016061288711668},{"t_us":34217706,"type":"arrival","trader":"noise","side_intent":"sell","u_accept":0.3544650008739437},{"t_us":34333094,"type":"arrival","trader":"noise","side_intent":"buy","u_accept":0.1571463600773092},{"t_us":34650740,"type":"arrival","trader":"noise","side_intent":"sell","u_accept":0.6073899786068764},{"t_us":34699030,"type":"arrival","trader":"noise","side_intent":"buy","u_accept":0.5302204138435459},{"t_us":34999563,"type":"arrival","trader":"informed","side_intent":null,"u_accept":null},{"t_us":35356117,"type":"arrival","trader":"noise","side_intent":"buy","u_accept":0.821578653146509},{"t_us":35403906,"type":"jump","size":-1},{"t_us":35765754,"type":"arrival","trader":"noise","side_intent":"sell","u_accept":0.28492683010152786},{"t_us":36007156,"type":"jump","size":2},{"t_us":36315542,"type":"arrival","trader":"informed","side_intent":null,"u_accept":null},{"t_us":36366991,"type":"arrival","trader":"noise","side_intent":"sell","u_accept":0.19798347099941516},{"t_us":36462480,"type":"arrival","trader":"noise","side_intent":"buy","u_accept":0.89344418801608},{"t_us":36696305,"type":"arrival","trader":"informed","side_intent":null,"u_accept":null},{"t_us":36768331,"type":"arrival","trader":"noise","side_intent":"sell","u_accept":0.7800075542920847},{"t_us":37675841,"type":"arrival","trader":"informed","side_intent":null,"u_accept":null},{"t_us":37924129,"type":"arrival","trader":"noise","side_intent":"sell","u_accept":0.09326883956616028},{"t_us":38051759,"type":"arrival","trader":"noise","side_intent":"buy","u_accept":0.2268004626430331},{"t_us":38151528,"type":"arrival","trader":"informed","side_intent":null,"u_accept":null},{"t_us":38249649,"type":"arrival","trader":"noise","side_intent":"sell","u_accept":0.8158323982343549},{"t_us":38541357,"type":"arrival","trader":"informed","side_intent":null,"u_accept":null},{"t_us":38664352,"type":"arrival","trader":"informed","side_intent":null,"u_accept":null},{"t_us":38843360,"type":"arrival","trader":"informed","side_intent":null,"u_accept":null},{"t_us":39249687,"type":"arrival","trader":"noise","side_intent":"sell","u_accept":0.07106237505690649},{"t_us":39500098,"type":"jump","size":-8},{"t_us":39686112,"type":"arrival","trader":"noise","side_intent":"sell","u_accept":0.5707408491055962},{"t_us":39902571,"type":"arrival","trader":"noise","side_intent":"buy","u_accept":0.1264281847255958},{"t_us":39944547,"type":"arrival","trader":"noise","side_intent":"buy","u_accept":0.5228542856110511},{"t_us":40164383,"type":"arrival","trader":"noise","side_intent":"sell","u_accept":0.9113163943495877},{"t_us":40347623,"type":"arrival","trader":"noise","side_intent":"sell","u_accept":0.9954309637961235},{"t_us":40364041,"type":"arrival","trader":"informed","side_intent":null,"u_accept":null},{"t_us":41267358,"type":"arrival","trader":"noise","side_intent":"sell","u_accept":0.820945744595362},{"t_us":41337766,"type":"arrival","trader":"noise","side_intent":"buy","u_accept":0.7635921678257668},{"t_us":42499342,"type":"arrival","trader":"noise","side_intent":"buy","u_accept":0.5300903304221419},{"t_us":42628725,"type":"arrival","trader":"noise","side_intent":"buy","u_accept":0.5933800078631732},{"t_us":43052298,"type":"arrival","trader":"noise","side_intent":"buy","u_accept":0.15010271415948784},{"t_us":43055195,"type":"arrival","trader":"noise","side_intent":"buy","u_accept":0.289929252048601},{"t_us":43071356,"type":"arrival","trader":"informed","side_intent":null,"u_accept":null},{"t_us":43182377,"type":"arrival","trader":"noise","side_intent":"sell","u_accept":0.6511208705133131},{"t_us":43460251,"type":"arrival","trader":"noise","side_intent":"buy","u_accept":0.7985883896566514},{"t_us":43756492,"type":"arrival","trader":"informed","side_intent":null,"u_accept":null},{"t_us":43839883,"type":"arrival","trader":"noise","side_intent":"sell","u_accept":0.7195624622907841},{"t_us":44409605,"type":"arrival","trader":"noise","side_intent":"sell","u_accept":0.914848979976099},{"t_us":44801648,"type":"arrival","trader":"noise","side_intent":"sell","u_accept":0.2740070662952845},{"t_us":44995470,"type":"arrival","trader":"noise","side_intent":"buy","u_accept":0.14818488845896627},{"t_us":45563412,"type":"arrival","trader":"noise","side_intent":"sell","u_accept":0.10433845348754733},{"t_us":45733300,"type":"arrival","trader":"informed","side_intent":null,"u_accept":null},{"t_us":46006079,"type":"arrival","trader":"noise","side_intent":"sell","u_accept":0.7421828460914799},{"t_us":46123560,"type":"arrival","trader":"noise","side_intent":"sell","u_accept":0.18698683865013754},{"t_us":46461731,"type":"arrival","trader":"informed","side_intent":null,"u_accept":null},{"t_us":46660922,"type":"arrival","trader":"informed","side_intent":null,"u_accept":null},{"t_us":47213636,"type":"arrival","trader":"noise","side_intent":"sell","u_accept":0.09600292334635518},{"t_us":47420186,"type":"arrival","trader":"noise","side_intent":"sell","u_accept":0.14983207089403794},{"t_us":47616178,"type":"arrival","trader":"informed","side_intent":null,"u_accept":null},{"t_us":47797287,"type":"arrival","trader":"noise","side_intent":"buy","u_accept":0.8664862395049395},{"t_us":48350620,"type":"arrival","trader":"informed","side_intent":null,"u_accept":null},{"t_us":48829293,"type":"arrival","trader":"noise","side_intent":"sell","u_accept":0.1972342099590687},{"t_us":49082043,"type":"arrival","trader":"noise","side_intent":"sell","u_accept":0.24263358535377477},{"t_us":49266955,"type":"arrival","trader":"noise","side_intent":"buy","u_accept":0.757989331679687},{"t_us":49529524,"type":"arrival","trader":"noise","side_intent":"buy","u_accept":0.176725328846571},{"t_us":49780515,"type":"arrival","trader":"noise","side_intent":"sell","u_accept":0.9364038903289595},{"t_us":49861490,"type":"arrival","trader":"noise","side_intent":"sell","u_accept":0.6906484164993352},{"t_us":50349260,"type":"arrival","trader":"noise","side_intent":"buy","u_accept":0.221391121111143},{"t_us":50568577,"type":"arrival","trader":"noise","side_intent":"buy","u_accept":0.7910748853516166},{"t_us":50757232,"type":"arrival","trader":"noise","side_intent":"sell","u_accept":0.4614192787971879},{"t_us":50800412,"type":"arrival","trader":"noise","side_intent":"sell","u_accept":0.033918893946267015},{"t_us":51153195,"type":"arrival","trader":"noise","side_intent":"sell","u_accept":0.5121754060537382},{"t_us":51701110,"type":"jump","size":7},{"t_us":51792175,"type":"arrival","trader":"noise","side_intent":"buy","u_accept":0.10260020687278781},{"t_us":51962170,"type":"arrival","trader":"noise","side_intent":"buy","u_accept":0.3720332539669716},{"t_us":52471392,"type":"arrival","trader":"noise","side_intent":"sell","u_accept":0.32402011195423674},{"t_us":52743453,"type":"arrival","trader":"noise","side_intent":"sell","u_accept":0.4444961178396083},{"t_us":52884613,"type":"jump","size":1},{"t_us":53622757,"type":"arrival","trader":"noise","side_intent":"buy","u_accept":0.8733784412131084},{"t_us":53673687,"type":"arrival","trader":"noise","side_intent":"buy","u_accept":0.9456989497382857},{"t_us":53705766,"type":"arrival","trader":"informed","side_intent":null,"u_accept":null},{"t_us":53713046,"type":"arrival","trader":"noise","side_intent":"sell","u_accept":0.7074304345387331},{"t_us":54278114,"type":"arrival","trader":"noise","side_intent":"sell","u_accept":0.13692419685724888},{"t_us":54678215,"type":"arrival","trader":"informed","side_intent":null,"u_accept":null},{"t_us":54956848,"type":"arrival","trader":"informed","side_intent":null,"u_accept":null},{"t_us":55123652,"type":"arrival","trader":"informed","side_intent":null,"u_accept":null},{"t_us":55145020,"type":"arrival","trader":"informed","side_intent":null,"u_accept":null},{"t_us":55308644,"type":"arrival","trader":"noise","side_intent":"sell","u_accept":0.6490112128267802},{"t_us":55370807,"type":"arrival","trader":"noise","side_intent":"buy","u_accept":0.11962830911502698},{"t_us":55636001,"type":"arrival","trader":"informed","side_intent":null,"u_accept":null},{"t_us":55640810,"type":"arrival","trader":"noise","side_intent":"buy","u_accept":0.948576166391121},{"t_us":55753926,"type":"arrival","trader":"noise","side_intent":"buy","u_accept":0.7671980331466423},{"t_us":55764506,"type":"arrival","trader":"noise","side_intent":"sell","u_accept":0.37677100734888713},{"t_us":55843102,"type":"arrival","trader":"informed","side_intent":null,"u_accept":null},{"t_us":56910837,"type":"arrival","trader":"noise","side_intent":"sell","u_accept":0.5571752141208673},{"t_us":57094490,"type":"arrival","trader":"noise","side_intent":"sell","u_accept":0.4406021853952029},{"t_us":57473888,"type":"arrival","trader":"noise","side_intent":"buy","u_accept":0.3612245034400715},{"t_us":57687598,"type":"arrival","trader":"noise","side_intent":"buy","u_accept":0.49486281482441785},{"t_us":57823563,"type":"arrival","trader":"noise","side_intent":"buy","u_accept":0.2751001705910229},{"t_us":57835453,"type":"arrival","trader":"informed","side_intent":null,"u_accept":null},{"t_us":58092257,"type":"arrival","trader":"informed","side_intent":null,"u_accept":null},{"t_us":58136375,"type":"jump","size":-7},{"t_us":58561843,"type":"arrival","trader":"noise","side_intent":"buy","u_accept":0.602450975936492},{"t_us":58577937,"type":"arrival","trader":"noise","side_intent":"sell","u_accept":0.9491104410789964},{"t_us":59039853,"type":"arrival","trader":"noise","side_intent":"buy","u_accept":0.7144031339010468},{"t_us":59389123,"type":"arrival","trader":"informed","side_intent":null,"u_accept":null},{"t_us":59499183,"type":"arrival","trader":"informed","side_intent":null,"u_accept":null},{"t_us":59514897,"type":"arrival","trader":"noise","side_intent":"buy","u_accept":0.40689934491405544}]}
